cps_hhbk/__init__.py
cps_hhbk/ky001.py
cps_hhbk/ky006.py
cps_hhbk/led.py
cps_hhbk/main.py
cps_hhbk-0.0.4.dist-info/METADATA
cps_hhbk-0.0.4.dist-info/WHEEL
cps_hhbk-0.0.4.dist-info/entry_points.txt
cps_hhbk-0.0.4.dist-info/top_level.txt
cps_hhbk-0.0.4.dist-info/RECORD
