Metadata-Version: 2.4
Name: cps-hhbk
Version: 0.0.4
Summary: Short description for the cps-hhbk project
Author-email: Maximilian Erkens <contact@max-erkens.de>
License: MIT
Keywords: cps,hhbk
Classifier: Programming Language :: Python
Classifier: Programming Language :: Python :: 3
Classifier: License :: OSI Approved :: MIT License
Classifier: Operating System :: OS Independent
Requires-Python: >=3.10
Requires-Dist: gpiozero
